.travis.yml
NOTICE.txt
README.rst
bootstrap.py
buildout.cfg
setup.cfg
setup.py
travis.cfg
docs/HISTORY.txt
docs/INSTALL.txt
docs/LICENSE.txt
eke/__init__.py
eke.site.egg-info/PKG-INFO
eke.site.egg-info/SOURCES.txt
eke.site.egg-info/dependency_links.txt
eke.site.egg-info/entry_points.txt
eke.site.egg-info/namespace_packages.txt
eke.site.egg-info/not-zip-safe
eke.site.egg-info/requires.txt
eke.site.egg-info/top_level.txt
eke/site/README.rst
eke/site/__init__.py
eke/site/config.py
eke/site/configure.zcml
eke/site/interfaces.py
eke/site/overrides.zcml
eke/site/testing.py
eke/site/upgrades.py
eke/site/upgrades.zcml
eke/site/utils.py
eke/site/browser/__init__.py
eke/site/browser/configure.zcml
eke/site/browser/rdf.py
eke/site/browser/views.py
eke/site/browser/images/person.gif
eke/site/browser/images/site-folder.gif
eke/site/browser/images/site.gif
eke/site/browser/templates/person.pt
eke/site/browser/templates/site.pt
eke/site/browser/templates/sitebytypesection.pt
eke/site/browser/templates/sitefolder.pt
eke/site/content/__init__.py
eke/site/content/configure.zcml
eke/site/content/person.py
eke/site/content/site.py
eke/site/content/sitefolder.py
eke/site/profiles/default/catalog.xml
eke/site/profiles/default/factorytool.xml
eke/site/profiles/default/metadata.xml
eke/site/profiles/default/rolemap.xml
eke/site/profiles/default/types.xml
eke/site/profiles/default/types/Person.xml
eke/site/profiles/default/types/Site.xml
eke/site/profiles/default/types/Site_Folder.xml
eke/site/tests/__init__.py
eke/site/tests/base.py
eke/site/tests/testDoctest.py
eke/site/tests/testSetup.py